LICENSE
README.rst
setup.py
bluexpress/connector.py
bluexpress/handler.py
bluexpress/settings.py
corona_bluexpress.egg-info/PKG-INFO
corona_bluexpress.egg-info/SOURCES.txt
corona_bluexpress.egg-info/dependency_links.txt
corona_bluexpress.egg-info/requires.txt
corona_bluexpress.egg-info/top_level.txt