Metadata-Version: 2.1
Name: corona-bluexpress
Version: 1.5.9
Summary: Django Bluexpress Integration
Home-page: https://gitlab.com/linets-projects/python-libraries/django-bluexpress/
Author: Corona Development Team
Author-email: rolguin@corona.cl
License: MIT
Platform: UNKNOWN
Requires-Python: >=3.7
License-File: LICENSE
